OpenVisus/LICENSE
OpenVisus/README.md
OpenVisus/VisusDataflowPy.py
OpenVisus/VisusDbPy.py
OpenVisus/VisusKernelPy.py
OpenVisus/VisusNodesPy.py
OpenVisus/_VisusDataflowPy.pyd
OpenVisus/_VisusDbPy.pyd
OpenVisus/_VisusKernelPy.pyd
OpenVisus/_VisusNodesPy.pyd
OpenVisus/__init__.py
OpenVisus/__main__.py
OpenVisus/convert.py
OpenVisus/dataset.py
OpenVisus/gui.py
OpenVisus/image_utils.py
OpenVisus/s3.py
OpenVisus/scripting_node.py
OpenVisus/setup.py
OpenVisus/test.txt
OpenVisus/utils.py
OpenVisus/viewer.py
OpenVisus/visus.config
OpenVisus/Copyrights/Cryptlite
OpenVisus/Copyrights/Curl
OpenVisus/Copyrights/DTL
OpenVisus/Copyrights/FreeImage
OpenVisus/Copyrights/LZ4
OpenVisus/Copyrights/LibJPEG
OpenVisus/Copyrights/LibJXR
OpenVisus/Copyrights/LibOpenJPEG
OpenVisus/Copyrights/LibPNG
OpenVisus/Copyrights/LibRawLite
OpenVisus/Copyrights/LibTIFF4
OpenVisus/Copyrights/LibWebP
OpenVisus/Copyrights/LibreSSL
OpenVisus/Copyrights/Python
OpenVisus/Copyrights/Qt
OpenVisus/Copyrights/TinyXml
OpenVisus/Copyrights/ZLib
OpenVisus/Copyrights/ilmbase
OpenVisus/Copyrights/openexr
OpenVisus/Samples/jupyter/Agricolture.ipynb
OpenVisus/Samples/jupyter/Climate.ipynb
OpenVisus/Samples/jupyter/Create HTTP Accessible Idx File.ipynb
OpenVisus/Samples/jupyter/Filters.ipynb
OpenVisus/Samples/jupyter/OpenVisus-Blank.ipynb
OpenVisus/Samples/jupyter/OpenVisus-Tutorial.ipynb
OpenVisus/Samples/jupyter/ReadAndView.ipynb
OpenVisus/Samples/jupyter/SpeedTest.ipynb
OpenVisus/Samples/jupyter/TestIdxBlockCompression.ipynb
OpenVisus/Samples/jupyter/TestIdxBlockCompression.xlsx
OpenVisus/Samples/jupyter/VisibleMale.ipynb
OpenVisus/Samples/jupyter/arecibo.ipynb
OpenVisus/Samples/jupyter/dataset_slice.ipynb
OpenVisus/Samples/jupyter/demo-slice-foam-dataset-from-cloud-sources.ipynb
OpenVisus/Samples/jupyter/nasa_conversion_example.ipynb
OpenVisus/Samples/jupyter/neon.ipynb
OpenVisus/Samples/jupyter/netcdf-tutorial1.ipynb
OpenVisus/Samples/jupyter/netcdf-tutorial2.ipynb
OpenVisus/Samples/jupyter/plot_statistics.ipynb
openvisusnogui-2.2.149.dist-info/licenses/LICENSE
openvisusnogui-2.2.149.dist-info/METADATA
openvisusnogui-2.2.149.dist-info/WHEEL
openvisusnogui-2.2.149.dist-info/top_level.txt
openvisusnogui-2.2.149.dist-info/RECORD
