Metadata-Version: 2.4
Name: openvisusnogui
Version: 2.2.149
Summary: ViSUS multiresolution I/O, analysis, and visualization system
Home-page: https://github.com/sci-visus/OpenVisus
Author: visus.net
Author-email: support@visus.net
License: BSD
Platform: Linux
Platform: OS-X
Platform: Windows
Requires-Python: >=3.6
License-File: LICENSE
Dynamic: author
Dynamic: author-email
Dynamic: home-page
Dynamic: license
Dynamic: license-file
Dynamic: platform
Dynamic: requires-python
Dynamic: summary
